<?xml version="1.0" encoding="utf-8" ?>
<dwsync>
<file name="_animated.less" server="srvc109.turhost.com" local="3665816368" remote="3662515740" Dst="-1" />
<file name="_bordered-pulled.less" server="srvc109.turhost.com" local="3665816368" remote="3662515740" Dst="-1" />
<file name="_core.less" server="srvc109.turhost.com" local="3665816368" remote="3662515740" Dst="-1" />
<file name="_fixed-width.less" server="srvc109.turhost.com" local="3665816368" remote="3662515740" Dst="-1" />
<file name="_icons.less" server="srvc109.turhost.com" local="3665816368" remote="3662515740" Dst="-1" />
<file name="_larger.less" server="srvc109.turhost.com" local="3665816369" remote="3662515740" Dst="-1" />
<file name="_list.less" server="srvc109.turhost.com" local="3665816369" remote="3662515740" Dst="-1" />
<file name="_mixins.less" server="srvc109.turhost.com" local="3665816369" remote="3662515740" Dst="-1" />
<file name="_rotated-flipped.less" server="srvc109.turhost.com" local="3665816369" remote="3662515740" Dst="-1" />
<file name="_screen-reader.less" server="srvc109.turhost.com" local="3665816369" remote="3662515740" Dst="-1" />
<file name="_shims.less" server="srvc109.turhost.com" local="3665816369" remote="3662515740" Dst="-1" />
<file name="_stacked.less" server="srvc109.turhost.com" local="3665816369" remote="3662515740" Dst="-1" />
<file name="_variables.less" server="srvc109.turhost.com" local="3665816370" remote="3662515740" Dst="-1" />
<file name="brands.css" server="srvc109.turhost.com" local="3665816420" remote="3664617540" Dst="-1" />
<file name="brands.less" server="srvc109.turhost.com" local="3665816370" remote="3662515740" Dst="-1" />
<file name="fontawesome.less" server="srvc109.turhost.com" local="3665816370" remote="3662515740" Dst="-1" />
<file name="fontawesome.css" server="srvc109.turhost.com" local="3665816423" remote="3664617540" Dst="-1" />
<file name="regular.css" server="srvc109.turhost.com" local="3665816421" remote="3664617540" Dst="-1" />
<file name="solid.css" server="srvc109.turhost.com" local="3665816425" remote="3664617540" Dst="-1" />
<file name="regular.less" server="srvc109.turhost.com" local="3665816371" remote="3662515740" Dst="-1" />
<file name="solid.less" server="srvc109.turhost.com" local="3665816371" remote="3662515740" Dst="-1" />
<file name="v4-shims.less" server="srvc109.turhost.com" local="3665816371" remote="3662515740" Dst="-1" />
<file name="v4-shims.css" server="srvc109.turhost.com" local="3665816425" remote="3664617540" Dst="-1" />
<file name="_animated.less" server="ftp.tulpartech.com/kahvegunlukleri.com/" local="132285953722252411" remote="132241445400000000" Dst="0" />
<file name="_bordered-pulled.less" server="ftp.tulpartech.com/kahvegunlukleri.com/" local="132285953724621936" remote="132241445400000000" Dst="0" />
<file name="_core.less" server="ftp.tulpartech.com/kahvegunlukleri.com/" local="132285953724921835" remote="132241445400000000" Dst="0" />
<file name="_fixed-width.less" server="ftp.tulpartech.com/kahvegunlukleri.com/" local="132285953738072786" remote="132241445400000000" Dst="0" />
<file name="_larger.less" server="ftp.tulpartech.com/kahvegunlukleri.com/" local="132285953738752566" remote="132241445400000000" Dst="0" />
<file name="_list.less" server="ftp.tulpartech.com/kahvegunlukleri.com/" local="132285953739898737" remote="132241445400000000" Dst="0" />
<file name="_mixins.less" server="ftp.tulpartech.com/kahvegunlukleri.com/" local="132285953740338589" remote="132241445400000000" Dst="0" />
<file name="_rotated-flipped.less" server="ftp.tulpartech.com/kahvegunlukleri.com/" local="132285953740858974" remote="132241445400000000" Dst="0" />
<file name="_screen-reader.less" server="ftp.tulpartech.com/kahvegunlukleri.com/" local="132285953743518831" remote="132241445400000000" Dst="0" />
<file name="_icons.less" server="ftp.tulpartech.com/kahvegunlukleri.com/" local="132285953769839538" remote="132241445400000000" Dst="0" />
<file name="_shims.less" server="ftp.tulpartech.com/kahvegunlukleri.com/" local="132285953778967191" remote="132241445400000000" Dst="0" />
<file name="_stacked.less" server="ftp.tulpartech.com/kahvegunlukleri.com/" local="132285953779267170" remote="132241445400000000" Dst="0" />
<file name="_variables.less" server="ftp.tulpartech.com/kahvegunlukleri.com/" local="132285953785166171" remote="132241445400000000" Dst="0" />
<file name="brands.less" server="ftp.tulpartech.com/kahvegunlukleri.com/" local="132285953785526045" remote="132241445400000000" Dst="0" />
<file name="brands.css" server="ftp.tulpartech.com/kahvegunlukleri.com/" local="132285953784766259" remote="132262463400000000" Dst="0" />
<file name="fontawesome.less" server="ftp.tulpartech.com/kahvegunlukleri.com/" local="132285953790514943" remote="132241445400000000" Dst="0" />
<file name="fontawesome.css" server="ftp.tulpartech.com/kahvegunlukleri.com/" local="132285953797472246" remote="132262463400000000" Dst="0" />
<file name="regular.less" server="ftp.tulpartech.com/kahvegunlukleri.com/" local="132285953798231974" remote="132241445400000000" Dst="0" />
<file name="regular.css" server="ftp.tulpartech.com/kahvegunlukleri.com/" local="132285953797292597" remote="132262463400000000" Dst="0" />
<file name="solid.less" server="ftp.tulpartech.com/kahvegunlukleri.com/" local="132285953809393605" remote="132241445400000000" Dst="0" />
<file name="solid.css" server="ftp.tulpartech.com/kahvegunlukleri.com/" local="132285953821727488" remote="132262463400000000" Dst="0" />
<file name="v4-shims.less" server="ftp.tulpartech.com/kahvegunlukleri.com/" local="132285953824802419" remote="132241445400000000" Dst="0" />
<file name="v4-shims.css" server="ftp.tulpartech.com/kahvegunlukleri.com/" local="132285953825942149" remote="132262463400000000" Dst="0" />
</dwsync>