<?xml version="1.0" encoding="utf-8" ?>
<dwsync>
<file name="500px.svg" server="srvc109.turhost.com" local="3665816377" remote="3662515740" Dst="-1" />
<file name="accessible-icon.svg" server="srvc109.turhost.com" local="3665816377" remote="3662515740" Dst="-1" />
<file name="accusoft.svg" server="srvc109.turhost.com" local="3665816378" remote="3662515740" Dst="-1" />
<file name="acquisitions-incorporated.svg" server="srvc109.turhost.com" local="3665816378" remote="3662515740" Dst="-1" />
<file name="adversal.svg" server="srvc109.turhost.com" local="3665816378" remote="3662515740" Dst="-1" />
<file name="adn.svg" server="srvc109.turhost.com" local="3665816378" remote="3662515740" Dst="-1" />
<file name="adobe.svg" server="srvc109.turhost.com" local="3665816378" remote="3662515740" Dst="-1" />
<file name="affiliatetheme.svg" server="srvc109.turhost.com" local="3665816379" remote="3662515740" Dst="-1" />
<file name="airbnb.svg" server="srvc109.turhost.com" local="3665816379" remote="3662515740" Dst="-1" />
<file name="algolia.svg" server="srvc109.turhost.com" local="3665816379" remote="3662515740" Dst="-1" />
<file name="amazon-pay.svg" server="srvc109.turhost.com" local="3665816379" remote="3662515740" Dst="-1" />
<file name="amazon.svg" server="srvc109.turhost.com" local="3665816379" remote="3662515740" Dst="-1" />
<file name="alipay.svg" server="srvc109.turhost.com" local="3665816379" remote="3662515740" Dst="-1" />
<file name="amilia.svg" server="srvc109.turhost.com" local="3665816379" remote="3662515740" Dst="-1" />
<file name="android.svg" server="srvc109.turhost.com" local="3665816379" remote="3662515740" Dst="-1" />
<file name="angellist.svg" server="srvc109.turhost.com" local="3665816379" remote="3662515740" Dst="-1" />
<file name="angrycreative.svg" server="srvc109.turhost.com" local="3665816380" remote="3662515740" Dst="-1" />
<file name="angular.svg" server="srvc109.turhost.com" local="3665816380" remote="3662515740" Dst="-1" />
<file name="app-store-ios.svg" server="srvc109.turhost.com" local="3665816380" remote="3662515740" Dst="-1" />
<file name="apper.svg" server="srvc109.turhost.com" local="3665816380" remote="3662515740" Dst="-1" />
<file name="apple-pay.svg" server="srvc109.turhost.com" local="3665816380" remote="3662515740" Dst="-1" />
<file name="app-store.svg" server="srvc109.turhost.com" local="3665816380" remote="3662515740" Dst="-1" />
<file name="apple.svg" server="srvc109.turhost.com" local="3665816380" remote="3662515740" Dst="-1" />
<file name="artstation.svg" server="srvc109.turhost.com" local="3665816380" remote="3662515740" Dst="-1" />
<file name="asymmetrik.svg" server="srvc109.turhost.com" local="3665816380" remote="3662515740" Dst="-1" />
<file name="autoprefixer.svg" server="srvc109.turhost.com" local="3665816381" remote="3662515740" Dst="-1" />
<file name="atlassian.svg" server="srvc109.turhost.com" local="3665816381" remote="3662515740" Dst="-1" />
<file name="audible.svg" server="srvc109.turhost.com" local="3665816381" remote="3662515740" Dst="-1" />
<file name="avianex.svg" server="srvc109.turhost.com" local="3665816381" remote="3662515740" Dst="-1" />
<file name="aviato.svg" server="srvc109.turhost.com" local="3665816381" remote="3662515740" Dst="-1" />
<file name="aws.svg" server="srvc109.turhost.com" local="3665816381" remote="3662515740" Dst="-1" />
<file name="behance-square.svg" server="srvc109.turhost.com" local="3665816382" remote="3662515740" Dst="-1" />
<file name="bandcamp.svg" server="srvc109.turhost.com" local="3665816382" remote="3662515740" Dst="-1" />
<file name="battle-net.svg" server="srvc109.turhost.com" local="3665816382" remote="3662515740" Dst="-1" />
<file name="behance.svg" server="srvc109.turhost.com" local="3665816382" remote="3662515740" Dst="-1" />
<file name="bimobject.svg" server="srvc109.turhost.com" local="3665816382" remote="3662515740" Dst="-1" />
<file name="bitbucket.svg" server="srvc109.turhost.com" local="3665816382" remote="3662515740" Dst="-1" />
<file name="bity.svg" server="srvc109.turhost.com" local="3665816383" remote="3662515740" Dst="-1" />
<file name="black-tie.svg" server="srvc109.turhost.com" local="3665816383" remote="3662515740" Dst="-1" />
<file name="bitcoin.svg" server="srvc109.turhost.com" local="3665816383" remote="3662515740" Dst="-1" />
<file name="blackberry.svg" server="srvc109.turhost.com" local="3665816383" remote="3662515740" Dst="-1" />
<file name="blogger-b.svg" server="srvc109.turhost.com" local="3665816383" remote="3662515740" Dst="-1" />
<file name="blogger.svg" server="srvc109.turhost.com" local="3665816383" remote="3662515740" Dst="-1" />
<file name="bootstrap.svg" server="srvc109.turhost.com" local="3665816383" remote="3662515740" Dst="-1" />
<file name="bluetooth-b.svg" server="srvc109.turhost.com" local="3665816383" remote="3662515740" Dst="-1" />
<file name="bluetooth.svg" server="srvc109.turhost.com" local="3665816383" remote="3662515740" Dst="-1" />
<file name="btc.svg" server="srvc109.turhost.com" local="3665816384" remote="3662515740" Dst="-1" />
<file name="buffer.svg" server="srvc109.turhost.com" local="3665816384" remote="3662515740" Dst="-1" />
<file name="buromobelexperte.svg" server="srvc109.turhost.com" local="3665816384" remote="3662515740" Dst="-1" />
<file name="cc-amazon-pay.svg" server="srvc109.turhost.com" local="3665816384" remote="3662515740" Dst="-1" />
<file name="buysellads.svg" server="srvc109.turhost.com" local="3665816385" remote="3662515740" Dst="-1" />
<file name="canadian-maple-leaf.svg" server="srvc109.turhost.com" local="3665816385" remote="3662515740" Dst="-1" />
<file name="cc-apple-pay.svg" server="srvc109.turhost.com" local="3665816385" remote="3662515740" Dst="-1" />
<file name="cc-diners-club.svg" server="srvc109.turhost.com" local="3665816385" remote="3662515740" Dst="-1" />
<file name="cc-amex.svg" server="srvc109.turhost.com" local="3665816385" remote="3662515740" Dst="-1" />
<file name="cc-discover.svg" server="srvc109.turhost.com" local="3665816385" remote="3662515740" Dst="-1" />
<file name="cc-jcb.svg" server="srvc109.turhost.com" local="3665816385" remote="3662515740" Dst="-1" />
<file name="cc-mastercard.svg" server="srvc109.turhost.com" local="3665816385" remote="3662515740" Dst="-1" />
<file name="cc-paypal.svg" server="srvc109.turhost.com" local="3665816386" remote="3662515740" Dst="-1" />
<file name="cc-visa.svg" server="srvc109.turhost.com" local="3665816386" remote="3662515740" Dst="-1" />
<file name="cc-stripe.svg" server="srvc109.turhost.com" local="3665816386" remote="3662515740" Dst="-1" />
<file name="centercode.svg" server="srvc109.turhost.com" local="3665816386" remote="3662515740" Dst="-1" />
<file name="centos.svg" server="srvc109.turhost.com" local="3665816386" remote="3662515740" Dst="-1" />
<file name="chrome.svg" server="srvc109.turhost.com" local="3665816386" remote="3662515740" Dst="-1" />
<file name="chromecast.svg" server="srvc109.turhost.com" local="3665816387" remote="3662515740" Dst="-1" />
<file name="cloudscale.svg" server="srvc109.turhost.com" local="3665816387" remote="3662515740" Dst="-1" />
<file name="cloudsmith.svg" server="srvc109.turhost.com" local="3665816387" remote="3662515740" Dst="-1" />
<file name="cloudversify.svg" server="srvc109.turhost.com" local="3665816387" remote="3662515740" Dst="-1" />
<file name="codepen.svg" server="srvc109.turhost.com" local="3665816387" remote="3662515740" Dst="-1" />
<file name="codiepie.svg" server="srvc109.turhost.com" local="3665816387" remote="3662515740" Dst="-1" />
<file name="confluence.svg" server="srvc109.turhost.com" local="3665816388" remote="3662515740" Dst="-1" />
<file name="contao.svg" server="srvc109.turhost.com" local="3665816388" remote="3662515740" Dst="-1" />
<file name="connectdevelop.svg" server="srvc109.turhost.com" local="3665816388" remote="3662515740" Dst="-1" />
<file name="creative-commons-by.svg" server="srvc109.turhost.com" local="3665816388" remote="3662515740" Dst="-1" />
<file name="cpanel.svg" server="srvc109.turhost.com" local="3665816388" remote="3662515740" Dst="-1" />
<file name="cotton-bureau.svg" server="srvc109.turhost.com" local="3665816388" remote="3662515740" Dst="-1" />
<file name="creative-commons-nc-eu.svg" server="srvc109.turhost.com" local="3665816389" remote="3662515740" Dst="-1" />
<file name="creative-commons-nc.svg" server="srvc109.turhost.com" local="3665816389" remote="3662515740" Dst="-1" />
<file name="creative-commons-nc-jp.svg" server="srvc109.turhost.com" local="3665816389" remote="3662515740" Dst="-1" />
<file name="creative-commons-nd.svg" server="srvc109.turhost.com" local="3665816389" remote="3662515740" Dst="-1" />
<file name="creative-commons-pd-alt.svg" server="srvc109.turhost.com" local="3665816389" remote="3662515740" Dst="-1" />
<file name="creative-commons-pd.svg" server="srvc109.turhost.com" local="3665816389" remote="3662515740" Dst="-1" />
<file name="creative-commons-sampling-plus.svg" server="srvc109.turhost.com" local="3665816390" remote="3662515740" Dst="-1" />
<file name="creative-commons-sa.svg" server="srvc109.turhost.com" local="3665816390" remote="3662515740" Dst="-1" />
<file name="creative-commons-remix.svg" server="srvc109.turhost.com" local="3665816390" remote="3662515740" Dst="-1" />
<file name="creative-commons-sampling.svg" server="srvc109.turhost.com" local="3665816390" remote="3662515740" Dst="-1" />
<file name="creative-commons-zero.svg" server="srvc109.turhost.com" local="3665816390" remote="3662515740" Dst="-1" />
<file name="creative-commons-share.svg" server="srvc109.turhost.com" local="3665816390" remote="3662515740" Dst="-1" />
<file name="css3-alt.svg" server="srvc109.turhost.com" local="3665816391" remote="3662515740" Dst="-1" />
<file name="creative-commons.svg" server="srvc109.turhost.com" local="3665816391" remote="3662515740" Dst="-1" />
<file name="critical-role.svg" server="srvc109.turhost.com" local="3665816391" remote="3662515740" Dst="-1" />
<file name="css3.svg" server="srvc109.turhost.com" local="3665816391" remote="3662515740" Dst="-1" />
<file name="d-and-d-beyond.svg" server="srvc109.turhost.com" local="3665816391" remote="3662515740" Dst="-1" />
<file name="cuttlefish.svg" server="srvc109.turhost.com" local="3665816391" remote="3662515740" Dst="-1" />
<file name="d-and-d.svg" server="srvc109.turhost.com" local="3665816392" remote="3662515740" Dst="-1" />
<file name="dashcube.svg" server="srvc109.turhost.com" local="3665816392" remote="3662515740" Dst="-1" />
<file name="delicious.svg" server="srvc109.turhost.com" local="3665816392" remote="3662515740" Dst="-1" />
<file name="deploydog.svg" server="srvc109.turhost.com" local="3665816392" remote="3662515740" Dst="-1" />
<file name="deskpro.svg" server="srvc109.turhost.com" local="3665816392" remote="3662515740" Dst="-1" />
<file name="dev.svg" server="srvc109.turhost.com" local="3665816392" remote="3662515740" Dst="-1" />
<file name="dhl.svg" server="srvc109.turhost.com" local="3665816393" remote="3662515740" Dst="-1" />
<file name="diaspora.svg" server="srvc109.turhost.com" local="3665816393" remote="3662515740" Dst="-1" />
<file name="deviantart.svg" server="srvc109.turhost.com" local="3665816393" remote="3662515740" Dst="-1" />
<file name="digg.svg" server="srvc109.turhost.com" local="3665816393" remote="3662515740" Dst="-1" />
<file name="digital-ocean.svg" server="srvc109.turhost.com" local="3665816393" remote="3662515740" Dst="-1" />
<file name="discord.svg" server="srvc109.turhost.com" local="3665816393" remote="3662515740" Dst="-1" />
<file name="discourse.svg" server="srvc109.turhost.com" local="3665816394" remote="3662515740" Dst="-1" />
<file name="dochub.svg" server="srvc109.turhost.com" local="3665816394" remote="3662515740" Dst="-1" />
<file name="docker.svg" server="srvc109.turhost.com" local="3665816394" remote="3662515740" Dst="-1" />
<file name="draft2digital.svg" server="srvc109.turhost.com" local="3665816394" remote="3662515740" Dst="-1" />
<file name="dribbble.svg" server="srvc109.turhost.com" local="3665816394" remote="3662515740" Dst="-1" />
<file name="dribbble-square.svg" server="srvc109.turhost.com" local="3665816394" remote="3662515740" Dst="-1" />
<file name="dropbox.svg" server="srvc109.turhost.com" local="3665816394" remote="3662515740" Dst="-1" />
<file name="drupal.svg" server="srvc109.turhost.com" local="3665816394" remote="3662515740" Dst="-1" />
<file name="dyalog.svg" server="srvc109.turhost.com" local="3665816394" remote="3662515740" Dst="-1" />
<file name="earlybirds.svg" server="srvc109.turhost.com" local="3665816395" remote="3662515740" Dst="-1" />
<file name="ebay.svg" server="srvc109.turhost.com" local="3665816395" remote="3662515740" Dst="-1" />
<file name="edge.svg" server="srvc109.turhost.com" local="3665816395" remote="3662515740" Dst="-1" />
<file name="ember.svg" server="srvc109.turhost.com" local="3665816395" remote="3662515740" Dst="-1" />
<file name="elementor.svg" server="srvc109.turhost.com" local="3665816395" remote="3662515740" Dst="-1" />
<file name="ello.svg" server="srvc109.turhost.com" local="3665816395" remote="3662515740" Dst="-1" />
<file name="empire.svg" server="srvc109.turhost.com" local="3665816396" remote="3662515740" Dst="-1" />
<file name="envira.svg" server="srvc109.turhost.com" local="3665816396" remote="3662515740" Dst="-1" />
<file name="erlang.svg" server="srvc109.turhost.com" local="3665816396" remote="3662515740" Dst="-1" />
<file name="ethereum.svg" server="srvc109.turhost.com" local="3665816396" remote="3662515740" Dst="-1" />
<file name="etsy.svg" server="srvc109.turhost.com" local="3665816396" remote="3662515740" Dst="-1" />
<file name="evernote.svg" server="srvc109.turhost.com" local="3665816396" remote="3662515740" Dst="-1" />
<file name="expeditedssl.svg" server="srvc109.turhost.com" local="3665816397" remote="3662515740" Dst="-1" />
<file name="facebook-f.svg" server="srvc109.turhost.com" local="3665816397" remote="3662515740" Dst="-1" />
<file name="facebook-messenger.svg" server="srvc109.turhost.com" local="3665816397" remote="3662515740" Dst="-1" />
<file name="facebook-square.svg" server="srvc109.turhost.com" local="3665816397" remote="3662515740" Dst="-1" />
<file name="facebook.svg" server="srvc109.turhost.com" local="3665816397" remote="3662515740" Dst="-1" />
<file name="fantasy-flight-games.svg" server="srvc109.turhost.com" local="3665816397" remote="3662515740" Dst="-1" />
<file name="fedex.svg" server="srvc109.turhost.com" local="3665816398" remote="3662515740" Dst="-1" />
<file name="fedora.svg" server="srvc109.turhost.com" local="3665816398" remote="3662515740" Dst="-1" />
<file name="figma.svg" server="srvc109.turhost.com" local="3665816398" remote="3662515740" Dst="-1" />
<file name="firefox.svg" server="srvc109.turhost.com" local="3665816398" remote="3662515740" Dst="-1" />
<file name="first-order-alt.svg" server="srvc109.turhost.com" local="3665816398" remote="3662515740" Dst="-1" />
<file name="first-order.svg" server="srvc109.turhost.com" local="3665816398" remote="3662515740" Dst="-1" />
<file name="flipboard.svg" server="srvc109.turhost.com" local="3665816399" remote="3662515740" Dst="-1" />
<file name="firstdraft.svg" server="srvc109.turhost.com" local="3665816399" remote="3662515740" Dst="-1" />
<file name="flickr.svg" server="srvc109.turhost.com" local="3665816399" remote="3662515740" Dst="-1" />
<file name="font-awesome-flag.svg" server="srvc109.turhost.com" local="3665816399" remote="3662515740" Dst="-1" />
<file name="fly.svg" server="srvc109.turhost.com" local="3665816399" remote="3662515740" Dst="-1" />
<file name="font-awesome-alt.svg" server="srvc109.turhost.com" local="3665816399" remote="3662515740" Dst="-1" />
<file name="font-awesome.svg" server="srvc109.turhost.com" local="3665816399" remote="3662515740" Dst="-1" />
<file name="fonticons-fi.svg" server="srvc109.turhost.com" local="3665816399" remote="3662515740" Dst="-1" />
<file name="font-awesome-logo-full.svg" server="srvc109.turhost.com" local="3665816399" remote="3662515740" Dst="-1" />
<file name="fonticons.svg" server="srvc109.turhost.com" local="3665816400" remote="3662515740" Dst="-1" />
<file name="fort-awesome.svg" server="srvc109.turhost.com" local="3665816400" remote="3662515740" Dst="-1" />
<file name="fort-awesome-alt.svg" server="srvc109.turhost.com" local="3665816400" remote="3662515740" Dst="-1" />
<file name="forumbee.svg" server="srvc109.turhost.com" local="3665816400" remote="3662515740" Dst="-1" />
<file name="free-code-camp.svg" server="srvc109.turhost.com" local="3665816400" remote="3662515740" Dst="-1" />
<file name="foursquare.svg" server="srvc109.turhost.com" local="3665816400" remote="3662515740" Dst="-1" />
<file name="freebsd.svg" server="srvc109.turhost.com" local="3665816401" remote="3662515740" Dst="-1" />
<file name="fulcrum.svg" server="srvc109.turhost.com" local="3665816401" remote="3662515740" Dst="-1" />
<file name="galactic-republic.svg" server="srvc109.turhost.com" local="3665816401" remote="3662515740" Dst="-1" />
<file name="get-pocket.svg" server="srvc109.turhost.com" local="3665816401" remote="3662515740" Dst="-1" />
<file name="gg-circle.svg" server="srvc109.turhost.com" local="3665816401" remote="3662515740" Dst="-1" />
<file name="galactic-senate.svg" server="srvc109.turhost.com" local="3665816401" remote="3662515740" Dst="-1" />
<file name="git-square.svg" server="srvc109.turhost.com" local="3665816402" remote="3662515740" Dst="-1" />
<file name="gg.svg" server="srvc109.turhost.com" local="3665816402" remote="3662515740" Dst="-1" />
<file name="git-alt.svg" server="srvc109.turhost.com" local="3665816402" remote="3662515740" Dst="-1" />
<file name="git.svg" server="srvc109.turhost.com" local="3665816402" remote="3662515740" Dst="-1" />
<file name="github-alt.svg" server="srvc109.turhost.com" local="3665816402" remote="3662515740" Dst="-1" />
<file name="github-square.svg" server="srvc109.turhost.com" local="3665816402" remote="3662515740" Dst="-1" />
<file name="gitlab.svg" server="srvc109.turhost.com" local="3665816403" remote="3662515740" Dst="-1" />
<file name="github.svg" server="srvc109.turhost.com" local="3665816403" remote="3662515740" Dst="-1" />
<file name="gitkraken.svg" server="srvc109.turhost.com" local="3665816403" remote="3662515740" Dst="-1" />
<file name="glide-g.svg" server="srvc109.turhost.com" local="3665816403" remote="3662515740" Dst="-1" />
<file name="glide.svg" server="srvc109.turhost.com" local="3665816403" remote="3662515740" Dst="-1" />
<file name="gitter.svg" server="srvc109.turhost.com" local="3665816403" remote="3662515740" Dst="-1" />
<file name="gofore.svg" server="srvc109.turhost.com" local="3665816404" remote="3662515740" Dst="-1" />
<file name="goodreads-g.svg" server="srvc109.turhost.com" local="3665816404" remote="3662515740" Dst="-1" />
<file name="goodreads.svg" server="srvc109.turhost.com" local="3665816404" remote="3662515740" Dst="-1" />
<file name="google-plus-g.svg" server="srvc109.turhost.com" local="3665816404" remote="3662515740" Dst="-1" />
<file name="google-drive.svg" server="srvc109.turhost.com" local="3665816404" remote="3662515740" Dst="-1" />
<file name="google-play.svg" server="srvc109.turhost.com" local="3665816404" remote="3662515740" Dst="-1" />
<file name="google-plus-square.svg" server="srvc109.turhost.com" local="3665816405" remote="3662515740" Dst="-1" />
<file name="google-plus.svg" server="srvc109.turhost.com" local="3665816405" remote="3662515740" Dst="-1" />
<file name="google-wallet.svg" server="srvc109.turhost.com" local="3665816405" remote="3662515740" Dst="-1" />
<file name="google.svg" server="srvc109.turhost.com" local="3665816405" remote="3662515740" Dst="-1" />
<file name="grav.svg" server="srvc109.turhost.com" local="3665816405" remote="3662515740" Dst="-1" />
<file name="gratipay.svg" server="srvc109.turhost.com" local="3665816405" remote="3662515740" Dst="-1" />
<file name="gripfire.svg" server="srvc109.turhost.com" local="3665816405" remote="3662515740" Dst="-1" />
<file name="gulp.svg" server="srvc109.turhost.com" local="3665816405" remote="3662515740" Dst="-1" />
<file name="grunt.svg" server="srvc109.turhost.com" local="3665816405" remote="3662515740" Dst="-1" />
<file name="hackerrank.svg" server="srvc109.turhost.com" local="3665816406" remote="3662515740" Dst="-1" />
<file name="hacker-news-square.svg" server="srvc109.turhost.com" local="3665816406" remote="3662515740" Dst="-1" />
<file name="hacker-news.svg" server="srvc109.turhost.com" local="3665816406" remote="3662515740" Dst="-1" />
<file name="hire-a-helper.svg" server="srvc109.turhost.com" local="3665816406" remote="3662515740" Dst="-1" />
<file name="hips.svg" server="srvc109.turhost.com" local="3665816406" remote="3662515740" Dst="-1" />
<file name="hooli.svg" server="srvc109.turhost.com" local="3665816406" remote="3662515740" Dst="-1" />
<file name="500px.svg" server="ftp.tulpartech.com/kahvegunlukleri.com/" local="132285954116336993" remote="132241445400000000" Dst="0" />
<file name="accessible-icon.svg" server="ftp.tulpartech.com/kahvegunlukleri.com/" local="132285954118802262" remote="132241445400000000" Dst="0" />
<file name="accusoft.svg" server="ftp.tulpartech.com/kahvegunlukleri.com/" local="132285954122713663" remote="132241445400000000" Dst="0" />
<file name="acquisitions-incorporated.svg" server="ftp.tulpartech.com/kahvegunlukleri.com/" local="132285954128768692" remote="132241445400000000" Dst="0" />
<file name="adn.svg" server="ftp.tulpartech.com/kahvegunlukleri.com/" local="132285954130041107" remote="132241445400000000" Dst="0" />
<file name="adobe.svg" server="ftp.tulpartech.com/kahvegunlukleri.com/" local="132285954135811629" remote="132241445400000000" Dst="0" />
<file name="adversal.svg" server="ftp.tulpartech.com/kahvegunlukleri.com/" local="132285954149523673" remote="132241445400000000" Dst="0" />
<file name="affiliatetheme.svg" server="ftp.tulpartech.com/kahvegunlukleri.com/" local="132285954154883569" remote="132241445400000000" Dst="0" />
<file name="airbnb.svg" server="ftp.tulpartech.com/kahvegunlukleri.com/" local="132285954155483844" remote="132241445400000000" Dst="0" />
<file name="algolia.svg" server="ftp.tulpartech.com/kahvegunlukleri.com/" local="132285954155953793" remote="132241445400000000" Dst="0" />
<file name="alipay.svg" server="ftp.tulpartech.com/kahvegunlukleri.com/" local="132285954161256326" remote="132241445400000000" Dst="0" />
<file name="amazon-pay.svg" server="ftp.tulpartech.com/kahvegunlukleri.com/" local="132285954165393908" remote="132241445400000000" Dst="0" />
<file name="amazon.svg" server="ftp.tulpartech.com/kahvegunlukleri.com/" local="132285954173493715" remote="132241445400000000" Dst="0" />
<file name="amilia.svg" server="ftp.tulpartech.com/kahvegunlukleri.com/" local="132285954180879446" remote="132241445400000000" Dst="0" />
<file name="android.svg" server="ftp.tulpartech.com/kahvegunlukleri.com/" local="132285954181709271" remote="132241445400000000" Dst="0" />
<file name="angellist.svg" server="ftp.tulpartech.com/kahvegunlukleri.com/" local="132285954182210012" remote="132241445400000000" Dst="0" />
<file name="angrycreative.svg" server="ftp.tulpartech.com/kahvegunlukleri.com/" local="132285954184798231" remote="132241445400000000" Dst="0" />
<file name="angular.svg" server="ftp.tulpartech.com/kahvegunlukleri.com/" local="132285954187301444" remote="132241445400000000" Dst="0" />
<file name="app-store-ios.svg" server="ftp.tulpartech.com/kahvegunlukleri.com/" local="132285954189101204" remote="132241445400000000" Dst="0" />
<file name="app-store.svg" server="ftp.tulpartech.com/kahvegunlukleri.com/" local="132285954189820978" remote="132241445400000000" Dst="0" />
<file name="apper.svg" server="ftp.tulpartech.com/kahvegunlukleri.com/" local="132285954190481195" remote="132241445400000000" Dst="0" />
<file name="apple-pay.svg" server="ftp.tulpartech.com/kahvegunlukleri.com/" local="132285954206592582" remote="132241445400000000" Dst="0" />
<file name="apple.svg" server="ftp.tulpartech.com/kahvegunlukleri.com/" local="132285954207273055" remote="132241445400000000" Dst="0" />
<file name="artstation.svg" server="ftp.tulpartech.com/kahvegunlukleri.com/" local="132285954208813723" remote="132241445400000000" Dst="0" />
<file name="asymmetrik.svg" server="ftp.tulpartech.com/kahvegunlukleri.com/" local="132285954212141591" remote="132241445400000000" Dst="0" />
<file name="atlassian.svg" server="ftp.tulpartech.com/kahvegunlukleri.com/" local="132285954219723301" remote="132241445400000000" Dst="0" />
<file name="audible.svg" server="ftp.tulpartech.com/kahvegunlukleri.com/" local="132285954220593007" remote="132241445400000000" Dst="0" />
<file name="autoprefixer.svg" server="ftp.tulpartech.com/kahvegunlukleri.com/" local="132285954220682979" remote="132241445400000000" Dst="0" />
<file name="avianex.svg" server="ftp.tulpartech.com/kahvegunlukleri.com/" local="132285954221062847" remote="132241445400000000" Dst="0" />
<file name="aviato.svg" server="ftp.tulpartech.com/kahvegunlukleri.com/" local="132285954221182870" remote="132241445400000000" Dst="0" />
<file name="aws.svg" server="ftp.tulpartech.com/kahvegunlukleri.com/" local="132285954221582837" remote="132241445400000000" Dst="0" />
<file name="bandcamp.svg" server="ftp.tulpartech.com/kahvegunlukleri.com/" local="132285954221782736" remote="132241445400000000" Dst="0" />
<file name="battle-net.svg" server="ftp.tulpartech.com/kahvegunlukleri.com/" local="132285954222101966" remote="132241445400000000" Dst="0" />
<file name="behance-square.svg" server="ftp.tulpartech.com/kahvegunlukleri.com/" local="132285954222291864" remote="132241445400000000" Dst="0" />
<file name="behance.svg" server="ftp.tulpartech.com/kahvegunlukleri.com/" local="132285954222603456" remote="132241445400000000" Dst="0" />
<file name="bimobject.svg" server="ftp.tulpartech.com/kahvegunlukleri.com/" local="132285954222864609" remote="132241445400000000" Dst="0" />
<file name="bitbucket.svg" server="ftp.tulpartech.com/kahvegunlukleri.com/" local="132285954223064531" remote="132241445400000000" Dst="0" />
<file name="bitcoin.svg" server="ftp.tulpartech.com/kahvegunlukleri.com/" local="132285954223354588" remote="132241445400000000" Dst="0" />
<file name="bity.svg" server="ftp.tulpartech.com/kahvegunlukleri.com/" local="132285954223615209" remote="132241445400000000" Dst="0" />
<file name="black-tie.svg" server="ftp.tulpartech.com/kahvegunlukleri.com/" local="132285954223855825" remote="132241445400000000" Dst="0" />
<file name="blackberry.svg" server="ftp.tulpartech.com/kahvegunlukleri.com/" local="132285954224245061" remote="132241445400000000" Dst="0" />
<file name="blogger-b.svg" server="ftp.tulpartech.com/kahvegunlukleri.com/" local="132285954224494847" remote="132241445400000000" Dst="0" />
<file name="blogger.svg" server="ftp.tulpartech.com/kahvegunlukleri.com/" local="132285954224825849" remote="132241445400000000" Dst="0" />
<file name="bluetooth-b.svg" server="ftp.tulpartech.com/kahvegunlukleri.com/" local="132285954225095696" remote="132241445400000000" Dst="0" />
<file name="bluetooth.svg" server="ftp.tulpartech.com/kahvegunlukleri.com/" local="132285954225311139" remote="132241445400000000" Dst="0" />
<file name="bootstrap.svg" server="ftp.tulpartech.com/kahvegunlukleri.com/" local="132285954225611203" remote="132241445400000000" Dst="0" />
<file name="btc.svg" server="ftp.tulpartech.com/kahvegunlukleri.com/" local="132285954225941468" remote="132241445400000000" Dst="0" />
<file name="buffer.svg" server="ftp.tulpartech.com/kahvegunlukleri.com/" local="132285954226162073" remote="132241445400000000" Dst="0" />
<file name="buromobelexperte.svg" server="ftp.tulpartech.com/kahvegunlukleri.com/" local="132285954226462526" remote="132241445400000000" Dst="0" />
<file name="buysellads.svg" server="ftp.tulpartech.com/kahvegunlukleri.com/" local="132285954226702466" remote="132241445400000000" Dst="0" />
<file name="canadian-maple-leaf.svg" server="ftp.tulpartech.com/kahvegunlukleri.com/" local="132285954227063154" remote="132241445400000000" Dst="0" />
<file name="cc-amazon-pay.svg" server="ftp.tulpartech.com/kahvegunlukleri.com/" local="132285954227262945" remote="132241445400000000" Dst="0" />
<file name="cc-amex.svg" server="ftp.tulpartech.com/kahvegunlukleri.com/" local="132285954227563434" remote="132241445400000000" Dst="0" />
<file name="cc-apple-pay.svg" server="ftp.tulpartech.com/kahvegunlukleri.com/" local="132285954227793232" remote="132241445400000000" Dst="0" />
<file name="cc-diners-club.svg" server="ftp.tulpartech.com/kahvegunlukleri.com/" local="132285954228073462" remote="132241445400000000" Dst="0" />
<file name="cc-discover.svg" server="ftp.tulpartech.com/kahvegunlukleri.com/" local="132285954228263390" remote="132241445400000000" Dst="0" />
<file name="cc-jcb.svg" server="ftp.tulpartech.com/kahvegunlukleri.com/" local="132285954228594162" remote="132241445400000000" Dst="0" />
<file name="cc-mastercard.svg" server="ftp.tulpartech.com/kahvegunlukleri.com/" local="132285954228802716" remote="132241445400000000" Dst="0" />
<file name="cc-paypal.svg" server="ftp.tulpartech.com/kahvegunlukleri.com/" local="132285954229122998" remote="132241445400000000" Dst="0" />
<file name="cc-stripe.svg" server="ftp.tulpartech.com/kahvegunlukleri.com/" local="132285954229373037" remote="132241445400000000" Dst="0" />
<file name="cc-visa.svg" server="ftp.tulpartech.com/kahvegunlukleri.com/" local="132285954229622926" remote="132241445400000000" Dst="0" />
<file name="centercode.svg" server="ftp.tulpartech.com/kahvegunlukleri.com/" local="132285954229882838" remote="132241445400000000" Dst="0" />
<file name="centos.svg" server="ftp.tulpartech.com/kahvegunlukleri.com/" local="132285954230152751" remote="132241445400000000" Dst="0" />
<file name="chrome.svg" server="ftp.tulpartech.com/kahvegunlukleri.com/" local="132285954230412666" remote="132241445400000000" Dst="0" />
<file name="chromecast.svg" server="ftp.tulpartech.com/kahvegunlukleri.com/" local="132285954230662585" remote="132241445400000000" Dst="0" />
<file name="cloudscale.svg" server="ftp.tulpartech.com/kahvegunlukleri.com/" local="132285954230862518" remote="132241445400000000" Dst="0" />
<file name="cloudsmith.svg" server="ftp.tulpartech.com/kahvegunlukleri.com/" local="132285954231152428" remote="132241445400000000" Dst="0" />
<file name="cloudversify.svg" server="ftp.tulpartech.com/kahvegunlukleri.com/" local="132285954231402348" remote="132241445400000000" Dst="0" />
<file name="codepen.svg" server="ftp.tulpartech.com/kahvegunlukleri.com/" local="132285954231652265" remote="132241445400000000" Dst="0" />
<file name="codiepie.svg" server="ftp.tulpartech.com/kahvegunlukleri.com/" local="132285954231906341" remote="132241445400000000" Dst="0" />
<file name="confluence.svg" server="ftp.tulpartech.com/kahvegunlukleri.com/" local="132285954232152565" remote="132241445400000000" Dst="0" />
<file name="connectdevelop.svg" server="ftp.tulpartech.com/kahvegunlukleri.com/" local="132285954232352501" remote="132241445400000000" Dst="0" />
<file name="contao.svg" server="ftp.tulpartech.com/kahvegunlukleri.com/" local="132285954232662401" remote="132241445400000000" Dst="0" />
<file name="cotton-bureau.svg" server="ftp.tulpartech.com/kahvegunlukleri.com/" local="132285954232912464" remote="132241445400000000" Dst="0" />
<file name="cpanel.svg" server="ftp.tulpartech.com/kahvegunlukleri.com/" local="132285954233182758" remote="132241445400000000" Dst="0" />
<file name="creative-commons-by.svg" server="ftp.tulpartech.com/kahvegunlukleri.com/" local="132285954233392493" remote="132241445400000000" Dst="0" />
<file name="creative-commons-nc-eu.svg" server="ftp.tulpartech.com/kahvegunlukleri.com/" local="132285954233692385" remote="132241445400000000" Dst="0" />
<file name="creative-commons-nc-jp.svg" server="ftp.tulpartech.com/kahvegunlukleri.com/" local="132285954233942309" remote="132241445400000000" Dst="0" />
<file name="creative-commons-nc.svg" server="ftp.tulpartech.com/kahvegunlukleri.com/" local="132285954234192278" remote="132241445400000000" Dst="0" />
<file name="creative-commons-nd.svg" server="ftp.tulpartech.com/kahvegunlukleri.com/" local="132285954234422300" remote="132241445400000000" Dst="0" />
<file name="creative-commons-pd.svg" server="ftp.tulpartech.com/kahvegunlukleri.com/" local="132285954237041975" remote="132241445400000000" Dst="0" />
<file name="creative-commons-pd-alt.svg" server="ftp.tulpartech.com/kahvegunlukleri.com/" local="132285954237421860" remote="132241445400000000" Dst="0" />
<file name="creative-commons-remix.svg" server="ftp.tulpartech.com/kahvegunlukleri.com/" local="132285954240509214" remote="132241445400000000" Dst="0" />
<file name="creative-commons-sa.svg" server="ftp.tulpartech.com/kahvegunlukleri.com/" local="132285954242835707" remote="132241445400000000" Dst="0" />
<file name="creative-commons-sampling-plus.svg" server="ftp.tulpartech.com/kahvegunlukleri.com/" local="132285954243275551" remote="132241445400000000" Dst="0" />
<file name="creative-commons-sampling.svg" server="ftp.tulpartech.com/kahvegunlukleri.com/" local="132285954243475490" remote="132241445400000000" Dst="0" />
<file name="creative-commons-share.svg" server="ftp.tulpartech.com/kahvegunlukleri.com/" local="132285954243735406" remote="132241445400000000" Dst="0" />
<file name="creative-commons-zero.svg" server="ftp.tulpartech.com/kahvegunlukleri.com/" local="132285954243995321" remote="132241445400000000" Dst="0" />
<file name="creative-commons.svg" server="ftp.tulpartech.com/kahvegunlukleri.com/" local="132285954244575997" remote="132241445400000000" Dst="0" />
<file name="css3-alt.svg" server="ftp.tulpartech.com/kahvegunlukleri.com/" local="132285954245021911" remote="132241445400000000" Dst="0" />
<file name="css3.svg" server="ftp.tulpartech.com/kahvegunlukleri.com/" local="132285954246580405" remote="132241445400000000" Dst="0" />
<file name="critical-role.svg" server="ftp.tulpartech.com/kahvegunlukleri.com/" local="132285954246988852" remote="132241445400000000" Dst="0" />
<file name="cuttlefish.svg" server="ftp.tulpartech.com/kahvegunlukleri.com/" local="132285954247479002" remote="132241445400000000" Dst="0" />
<file name="d-and-d.svg" server="ftp.tulpartech.com/kahvegunlukleri.com/" local="132285954248029278" remote="132241445400000000" Dst="0" />
<file name="d-and-d-beyond.svg" server="ftp.tulpartech.com/kahvegunlukleri.com/" local="132285954250595749" remote="132241445400000000" Dst="0" />
<file name="delicious.svg" server="ftp.tulpartech.com/kahvegunlukleri.com/" local="132285954255836389" remote="132241445400000000" Dst="0" />
<file name="dashcube.svg" server="ftp.tulpartech.com/kahvegunlukleri.com/" local="132285954259783778" remote="132241445400000000" Dst="0" />
<file name="deploydog.svg" server="ftp.tulpartech.com/kahvegunlukleri.com/" local="132285954271389172" remote="132241445400000000" Dst="0" />
<file name="dev.svg" server="ftp.tulpartech.com/kahvegunlukleri.com/" local="132285954272361726" remote="132241445400000000" Dst="0" />
<file name="deviantart.svg" server="ftp.tulpartech.com/kahvegunlukleri.com/" local="132285954275640060" remote="132241445400000000" Dst="0" />
<file name="dhl.svg" server="ftp.tulpartech.com/kahvegunlukleri.com/" local="132285954282016704" remote="132241445400000000" Dst="0" />
<file name="diaspora.svg" server="ftp.tulpartech.com/kahvegunlukleri.com/" local="132285954283210018" remote="132241445400000000" Dst="0" />
<file name="digg.svg" server="ftp.tulpartech.com/kahvegunlukleri.com/" local="132285954287068972" remote="132241445400000000" Dst="0" />
<file name="digital-ocean.svg" server="ftp.tulpartech.com/kahvegunlukleri.com/" local="132285954290973486" remote="132241445400000000" Dst="0" />
<file name="discord.svg" server="ftp.tulpartech.com/kahvegunlukleri.com/" local="132285954294256027" remote="132241445400000000" Dst="0" />
<file name="deskpro.svg" server="ftp.tulpartech.com/kahvegunlukleri.com/" local="132285954295354605" remote="132241445400000000" Dst="0" />
<file name="dochub.svg" server="ftp.tulpartech.com/kahvegunlukleri.com/" local="132285954297962969" remote="132241445400000000" Dst="0" />
<file name="discourse.svg" server="ftp.tulpartech.com/kahvegunlukleri.com/" local="132285954302680477" remote="132241445400000000" Dst="0" />
<file name="docker.svg" server="ftp.tulpartech.com/kahvegunlukleri.com/" local="132285954305021302" remote="132241445400000000" Dst="0" />
<file name="dribbble-square.svg" server="ftp.tulpartech.com/kahvegunlukleri.com/" local="132285954306990262" remote="132241445400000000" Dst="0" />
<file name="draft2digital.svg" server="ftp.tulpartech.com/kahvegunlukleri.com/" local="132285954307219870" remote="132241445400000000" Dst="0" />
<file name="dropbox.svg" server="ftp.tulpartech.com/kahvegunlukleri.com/" local="132285954308169594" remote="132241445400000000" Dst="0" />
<file name="dribbble.svg" server="ftp.tulpartech.com/kahvegunlukleri.com/" local="132285954308219585" remote="132241445400000000" Dst="0" />
<file name="drupal.svg" server="ftp.tulpartech.com/kahvegunlukleri.com/" local="132285954310791537" remote="132241445400000000" Dst="0" />
<file name="dyalog.svg" server="ftp.tulpartech.com/kahvegunlukleri.com/" local="132285954313213673" remote="132241445400000000" Dst="0" />
<file name="earlybirds.svg" server="ftp.tulpartech.com/kahvegunlukleri.com/" local="132285954318414496" remote="132241445400000000" Dst="0" />
<file name="ebay.svg" server="ftp.tulpartech.com/kahvegunlukleri.com/" local="132285954318644369" remote="132241445400000000" Dst="0" />
<file name="elementor.svg" server="ftp.tulpartech.com/kahvegunlukleri.com/" local="132285954326222029" remote="132241445400000000" Dst="0" />
<file name="ello.svg" server="ftp.tulpartech.com/kahvegunlukleri.com/" local="132285954328673858" remote="132241445400000000" Dst="0" />
<file name="edge.svg" server="ftp.tulpartech.com/kahvegunlukleri.com/" local="132285954336608029" remote="132241445400000000" Dst="0" />
<file name="ember.svg" server="ftp.tulpartech.com/kahvegunlukleri.com/" local="132285954337159972" remote="132241445400000000" Dst="0" />
<file name="empire.svg" server="ftp.tulpartech.com/kahvegunlukleri.com/" local="132285954339745844" remote="132241445400000000" Dst="0" />
<file name="envira.svg" server="ftp.tulpartech.com/kahvegunlukleri.com/" local="132285954342253344" remote="132241445400000000" Dst="0" />
<file name="erlang.svg" server="ftp.tulpartech.com/kahvegunlukleri.com/" local="132285954346908829" remote="132241445400000000" Dst="0" />
<file name="etsy.svg" server="ftp.tulpartech.com/kahvegunlukleri.com/" local="132285954347538601" remote="132241445400000000" Dst="0" />
<file name="ethereum.svg" server="ftp.tulpartech.com/kahvegunlukleri.com/" local="132285954349700520" remote="132241445400000000" Dst="0" />
<file name="expeditedssl.svg" server="ftp.tulpartech.com/kahvegunlukleri.com/" local="132285954350390582" remote="132241445400000000" Dst="0" />
<file name="facebook-f.svg" server="ftp.tulpartech.com/kahvegunlukleri.com/" local="132285954350920655" remote="132241445400000000" Dst="0" />
<file name="facebook-messenger.svg" server="ftp.tulpartech.com/kahvegunlukleri.com/" local="132285954351650997" remote="132241445400000000" Dst="0" />
<file name="evernote.svg" server="ftp.tulpartech.com/kahvegunlukleri.com/" local="132285954356329786" remote="132241445400000000" Dst="0" />
<file name="facebook-square.svg" server="ftp.tulpartech.com/kahvegunlukleri.com/" local="132285954358990595" remote="132241445400000000" Dst="0" />
<file name="fantasy-flight-games.svg" server="ftp.tulpartech.com/kahvegunlukleri.com/" local="132285954359550389" remote="132241445400000000" Dst="0" />
<file name="fedex.svg" server="ftp.tulpartech.com/kahvegunlukleri.com/" local="132285954360080987" remote="132241445400000000" Dst="0" />
<file name="facebook.svg" server="ftp.tulpartech.com/kahvegunlukleri.com/" local="132285954361594787" remote="132241445400000000" Dst="0" />
<file name="figma.svg" server="ftp.tulpartech.com/kahvegunlukleri.com/" local="132285954362519976" remote="132241445400000000" Dst="0" />
<file name="fedora.svg" server="ftp.tulpartech.com/kahvegunlukleri.com/" local="132285954364883886" remote="132241445400000000" Dst="0" />
<file name="firefox.svg" server="ftp.tulpartech.com/kahvegunlukleri.com/" local="132285954367938525" remote="132241445400000000" Dst="0" />
<file name="first-order-alt.svg" server="ftp.tulpartech.com/kahvegunlukleri.com/" local="132285954370154727" remote="132241445400000000" Dst="0" />
<file name="firstdraft.svg" server="ftp.tulpartech.com/kahvegunlukleri.com/" local="132285954370804376" remote="132241445400000000" Dst="0" />
<file name="flickr.svg" server="ftp.tulpartech.com/kahvegunlukleri.com/" local="132285954371704640" remote="132241445400000000" Dst="0" />
<file name="first-order.svg" server="ftp.tulpartech.com/kahvegunlukleri.com/" local="132285954371864282" remote="132241445400000000" Dst="0" />
<file name="flipboard.svg" server="ftp.tulpartech.com/kahvegunlukleri.com/" local="132285954372330848" remote="132241445400000000" Dst="0" />
<file name="fly.svg" server="ftp.tulpartech.com/kahvegunlukleri.com/" local="132285954372920749" remote="132241445400000000" Dst="0" />
<file name="font-awesome-alt.svg" server="ftp.tulpartech.com/kahvegunlukleri.com/" local="132285954375068188" remote="132241445400000000" Dst="0" />
<file name="font-awesome-flag.svg" server="ftp.tulpartech.com/kahvegunlukleri.com/" local="132285954377208625" remote="132241445400000000" Dst="0" />
<file name="font-awesome-logo-full.svg" server="ftp.tulpartech.com/kahvegunlukleri.com/" local="132285954379418923" remote="132241445400000000" Dst="0" />
<file name="fonticons-fi.svg" server="ftp.tulpartech.com/kahvegunlukleri.com/" local="132285954382257732" remote="132241445400000000" Dst="0" />
<file name="fonticons.svg" server="ftp.tulpartech.com/kahvegunlukleri.com/" local="132285954390169612" remote="132241445400000000" Dst="0" />
<file name="font-awesome.svg" server="ftp.tulpartech.com/kahvegunlukleri.com/" local="132285954394653898" remote="132241445400000000" Dst="0" />
<file name="fort-awesome.svg" server="ftp.tulpartech.com/kahvegunlukleri.com/" local="132285954396395037" remote="132241445400000000" Dst="0" />
<file name="fort-awesome-alt.svg" server="ftp.tulpartech.com/kahvegunlukleri.com/" local="132285954396504975" remote="132241445400000000" Dst="0" />
<file name="forumbee.svg" server="ftp.tulpartech.com/kahvegunlukleri.com/" local="132285954396954822" remote="132241445400000000" Dst="0" />
<file name="foursquare.svg" server="ftp.tulpartech.com/kahvegunlukleri.com/" local="132285954397034793" remote="132241445400000000" Dst="0" />
<file name="free-code-camp.svg" server="ftp.tulpartech.com/kahvegunlukleri.com/" local="132285954397414729" remote="132241445400000000" Dst="0" />
<file name="fulcrum.svg" server="ftp.tulpartech.com/kahvegunlukleri.com/" local="132285954404543937" remote="132241445400000000" Dst="0" />
<file name="freebsd.svg" server="ftp.tulpartech.com/kahvegunlukleri.com/" local="132285954404743933" remote="132241445400000000" Dst="0" />
<file name="galactic-republic.svg" server="ftp.tulpartech.com/kahvegunlukleri.com/" local="132285954405263741" remote="132241445400000000" Dst="0" />
<file name="galactic-senate.svg" server="ftp.tulpartech.com/kahvegunlukleri.com/" local="132285954405363717" remote="132241445400000000" Dst="0" />
<file name="get-pocket.svg" server="ftp.tulpartech.com/kahvegunlukleri.com/" local="132285954405733592" remote="132241445400000000" Dst="0" />
<file name="gg.svg" server="ftp.tulpartech.com/kahvegunlukleri.com/" local="132285954407220836" remote="132241445400000000" Dst="0" />
<file name="gg-circle.svg" server="ftp.tulpartech.com/kahvegunlukleri.com/" local="132285954408010057" remote="132241445400000000" Dst="0" />
<file name="git-square.svg" server="ftp.tulpartech.com/kahvegunlukleri.com/" local="132285954408738844" remote="132241445400000000" Dst="0" />
<file name="git-alt.svg" server="ftp.tulpartech.com/kahvegunlukleri.com/" local="132285954410087541" remote="132241445400000000" Dst="0" />
<file name="github-alt.svg" server="ftp.tulpartech.com/kahvegunlukleri.com/" local="132285954410717454" remote="132241445400000000" Dst="0" />
<file name="github-square.svg" server="ftp.tulpartech.com/kahvegunlukleri.com/" local="132285954419429519" remote="132241445400000000" Dst="0" />
<file name="github.svg" server="ftp.tulpartech.com/kahvegunlukleri.com/" local="132285954425407469" remote="132241445400000000" Dst="0" />
<file name="git.svg" server="ftp.tulpartech.com/kahvegunlukleri.com/" local="132285954425497482" remote="132241445400000000" Dst="0" />
<file name="gitkraken.svg" server="ftp.tulpartech.com/kahvegunlukleri.com/" local="132285954425927330" remote="132241445400000000" Dst="0" />
<file name="gitlab.svg" server="ftp.tulpartech.com/kahvegunlukleri.com/" local="132285954426007302" remote="132241445400000000" Dst="0" />
<file name="gitter.svg" server="ftp.tulpartech.com/kahvegunlukleri.com/" local="132285954426407175" remote="132241445400000000" Dst="0" />
<file name="glide-g.svg" server="ftp.tulpartech.com/kahvegunlukleri.com/" local="132285954426507142" remote="132241445400000000" Dst="0" />
<file name="glide.svg" server="ftp.tulpartech.com/kahvegunlukleri.com/" local="132285954427017094" remote="132241445400000000" Dst="0" />
<file name="goodreads-g.svg" server="ftp.tulpartech.com/kahvegunlukleri.com/" local="132285954428347330" remote="132241445400000000" Dst="0" />
<file name="gofore.svg" server="ftp.tulpartech.com/kahvegunlukleri.com/" local="132285954429108233" remote="132241445400000000" Dst="0" />
<file name="goodreads.svg" server="ftp.tulpartech.com/kahvegunlukleri.com/" local="132285954429198214" remote="132241445400000000" Dst="0" />
<file name="google-drive.svg" server="ftp.tulpartech.com/kahvegunlukleri.com/" local="132285954429688037" remote="132241445400000000" Dst="0" />
<file name="google-play.svg" server="ftp.tulpartech.com/kahvegunlukleri.com/" local="132285954429807999" remote="132241445400000000" Dst="0" />
<file name="google-plus-g.svg" server="ftp.tulpartech.com/kahvegunlukleri.com/" local="132285954430187881" remote="132241445400000000" Dst="0" />
<file name="google-plus-square.svg" server="ftp.tulpartech.com/kahvegunlukleri.com/" local="132285954430257854" remote="132241445400000000" Dst="0" />
<file name="google-wallet.svg" server="ftp.tulpartech.com/kahvegunlukleri.com/" local="132285954437134233" remote="132241445400000000" Dst="0" />
<file name="google.svg" server="ftp.tulpartech.com/kahvegunlukleri.com/" local="132285954438604636" remote="132241445400000000" Dst="0" />
<file name="google-plus.svg" server="ftp.tulpartech.com/kahvegunlukleri.com/" local="132285954439224423" remote="132241445400000000" Dst="0" />
<file name="gratipay.svg" server="ftp.tulpartech.com/kahvegunlukleri.com/" local="132285954439314395" remote="132241445400000000" Dst="0" />
<file name="gripfire.svg" server="ftp.tulpartech.com/kahvegunlukleri.com/" local="132285954440214172" remote="132241445400000000" Dst="0" />
<file name="grunt.svg" server="ftp.tulpartech.com/kahvegunlukleri.com/" local="132285954441835961" remote="132241445400000000" Dst="0" />
<file name="grav.svg" server="ftp.tulpartech.com/kahvegunlukleri.com/" local="132285954442055973" remote="132241445400000000" Dst="0" />
<file name="hacker-news-square.svg" server="ftp.tulpartech.com/kahvegunlukleri.com/" local="132285954444766546" remote="132241445400000000" Dst="0" />
<file name="hacker-news.svg" server="ftp.tulpartech.com/kahvegunlukleri.com/" local="132285954445416850" remote="132241445400000000" Dst="0" />
<file name="gulp.svg" server="ftp.tulpartech.com/kahvegunlukleri.com/" local="132285954445506718" remote="132241445400000000" Dst="0" />
<file name="hips.svg" server="ftp.tulpartech.com/kahvegunlukleri.com/" local="132285954446026541" remote="132241445400000000" Dst="0" />
<file name="hackerrank.svg" server="ftp.tulpartech.com/kahvegunlukleri.com/" local="132285954448069972" remote="132241445400000000" Dst="0" />
<file name="hooli.svg" server="ftp.tulpartech.com/kahvegunlukleri.com/" local="132285954453919164" remote="132241445400000000" Dst="0" />
<file name="hire-a-helper.svg" server="ftp.tulpartech.com/kahvegunlukleri.com/" local="132285954455166803" remote="132241445400000000" Dst="0" />
<file name="hornbill.svg" server="ftp.tulpartech.com/kahvegunlukleri.com/" local="132285954459624467" remote="132241445400000000" Dst="0" />
<file name="hotjar.svg" server="ftp.tulpartech.com/kahvegunlukleri.com/" local="132285954461254539" remote="132241445400000000" Dst="0" />
<file name="houzz.svg" server="ftp.tulpartech.com/kahvegunlukleri.com/" local="132285954461654403" remote="132241445400000000" Dst="0" />
<file name="html5.svg" server="ftp.tulpartech.com/kahvegunlukleri.com/" local="132285954462124235" remote="132241445400000000" Dst="0" />
<file name="hubspot.svg" server="ftp.tulpartech.com/kahvegunlukleri.com/" local="132285954462334513" remote="132241445400000000" Dst="0" />
<file name="imdb.svg" server="ftp.tulpartech.com/kahvegunlukleri.com/" local="132285954462714047" remote="132241445400000000" Dst="0" />
<file name="intercom.svg" server="ftp.tulpartech.com/kahvegunlukleri.com/" local="132285954463483486" remote="132241445400000000" Dst="0" />
<file name="instagram.svg" server="ftp.tulpartech.com/kahvegunlukleri.com/" local="132285954463663447" remote="132241445400000000" Dst="0" />
<file name="invision.svg" server="ftp.tulpartech.com/kahvegunlukleri.com/" local="132285954468679780" remote="132241445400000000" Dst="0" />
<file name="internet-explorer.svg" server="ftp.tulpartech.com/kahvegunlukleri.com/" local="132285954469129774" remote="132241445400000000" Dst="0" />
<file name="ioxhost.svg" server="ftp.tulpartech.com/kahvegunlukleri.com/" local="132285954469319678" remote="132241445400000000" Dst="0" />
<file name="itch-io.svg" server="ftp.tulpartech.com/kahvegunlukleri.com/" local="132285954469599475" remote="132241445400000000" Dst="0" />
<file name="itunes-note.svg" server="ftp.tulpartech.com/kahvegunlukleri.com/" local="132285954469859390" remote="132241445400000000" Dst="0" />
<file name="java.svg" server="ftp.tulpartech.com/kahvegunlukleri.com/" local="132285954470616201" remote="132241446000000000" Dst="0" />
<file name="jedi-order.svg" server="ftp.tulpartech.com/kahvegunlukleri.com/" local="132285954471235828" remote="132241446000000000" Dst="0" />
<file name="itunes.svg" server="ftp.tulpartech.com/kahvegunlukleri.com/" local="132285954472695908" remote="132241446000000000" Dst="0" />
<file name="jenkins.svg" server="ftp.tulpartech.com/kahvegunlukleri.com/" local="132285954475082009" remote="132241446000000000" Dst="0" />
<file name="jira.svg" server="ftp.tulpartech.com/kahvegunlukleri.com/" local="132285954475491862" remote="132241446000000000" Dst="0" />
<file name="joget.svg" server="ftp.tulpartech.com/kahvegunlukleri.com/" local="132285954475681798" remote="132241446000000000" Dst="0" />
<file name="js-square.svg" server="ftp.tulpartech.com/kahvegunlukleri.com/" local="132285954476241701" remote="132241446000000000" Dst="0" />
<file name="joomla.svg" server="ftp.tulpartech.com/kahvegunlukleri.com/" local="132285954478511285" remote="132241446000000000" Dst="0" />
<file name="kaggle.svg" server="ftp.tulpartech.com/kahvegunlukleri.com/" local="132285954478931270" remote="132241446000000000" Dst="0" />
<file name="jsfiddle.svg" server="ftp.tulpartech.com/kahvegunlukleri.com/" local="132285954478051435" remote="132241446000000000" Dst="0" />
<file name="js.svg" server="ftp.tulpartech.com/kahvegunlukleri.com/" local="132285954479191070" remote="132241446000000000" Dst="0" />
<file name="keycdn.svg" server="ftp.tulpartech.com/kahvegunlukleri.com/" local="132285954479570947" remote="132241446000000000" Dst="0" />
<file name="kickstarter-k.svg" server="ftp.tulpartech.com/kahvegunlukleri.com/" local="132285954479640997" remote="132241446000000000" Dst="0" />
<file name="kickstarter.svg" server="ftp.tulpartech.com/kahvegunlukleri.com/" local="132285954480060984" remote="132241446000000000" Dst="0" />
<file name="korvue.svg" server="ftp.tulpartech.com/kahvegunlukleri.com/" local="132285954482300238" remote="132241446000000000" Dst="0" />
<file name="laravel.svg" server="ftp.tulpartech.com/kahvegunlukleri.com/" local="132285954482470172" remote="132241446000000000" Dst="0" />
<file name="lastfm.svg" server="ftp.tulpartech.com/kahvegunlukleri.com/" local="132285954483270544" remote="132241446000000000" Dst="0" />
<file name="leanpub.svg" server="ftp.tulpartech.com/kahvegunlukleri.com/" local="132285954484980937" remote="132241446000000000" Dst="0" />
<file name="lastfm-square.svg" server="ftp.tulpartech.com/kahvegunlukleri.com/" local="132285954485551184" remote="132241446000000000" Dst="0" />
<file name="less.svg" server="ftp.tulpartech.com/kahvegunlukleri.com/" local="132285954488013128" remote="132241446000000000" Dst="0" />
<file name="keybase.svg" server="ftp.tulpartech.com/kahvegunlukleri.com/" local="132285954490628847" remote="132241446000000000" Dst="0" />
<file name="linkedin.svg" server="ftp.tulpartech.com/kahvegunlukleri.com/" local="132285954491808136" remote="132241446000000000" Dst="0" />
<file name="linkedin-in.svg" server="ftp.tulpartech.com/kahvegunlukleri.com/" local="132285954492489127" remote="132241446000000000" Dst="0" />
<file name="linode.svg" server="ftp.tulpartech.com/kahvegunlukleri.com/" local="132285954493019129" remote="132241446000000000" Dst="0" />
<file name="lyft.svg" server="ftp.tulpartech.com/kahvegunlukleri.com/" local="132285954493548761" remote="132241446000000000" Dst="0" />
<file name="line.svg" server="ftp.tulpartech.com/kahvegunlukleri.com/" local="132285954494048600" remote="132241446000000000" Dst="0" />
<file name="magento.svg" server="ftp.tulpartech.com/kahvegunlukleri.com/" local="132285954494398484" remote="132241446000000000" Dst="0" />
<file name="mailchimp.svg" server="ftp.tulpartech.com/kahvegunlukleri.com/" local="132285954494658399" remote="132241446000000000" Dst="0" />
<file name="mandalorian.svg" server="ftp.tulpartech.com/kahvegunlukleri.com/" local="132285954494918321" remote="132241446000000000" Dst="0" />
<file name="markdown.svg" server="ftp.tulpartech.com/kahvegunlukleri.com/" local="132285954495208226" remote="132241446000000000" Dst="0" />
<file name="mastodon.svg" server="ftp.tulpartech.com/kahvegunlukleri.com/" local="132285954495468135" remote="132241446000000000" Dst="0" />
<file name="maxcdn.svg" server="ftp.tulpartech.com/kahvegunlukleri.com/" local="132285954495738051" remote="132241446000000000" Dst="0" />
<file name="linux.svg" server="ftp.tulpartech.com/kahvegunlukleri.com/" local="132285954495788034" remote="132241446000000000" Dst="0" />
<file name="medapps.svg" server="ftp.tulpartech.com/kahvegunlukleri.com/" local="132285954496007963" remote="132241446000000000" Dst="0" />
<file name="medium.svg" server="ftp.tulpartech.com/kahvegunlukleri.com/" local="132285954501153648" remote="132241446000000000" Dst="0" />
<file name="medrt.svg" server="ftp.tulpartech.com/kahvegunlukleri.com/" local="132285954501593453" remote="132241446000000000" Dst="0" />
<file name="megaport.svg" server="ftp.tulpartech.com/kahvegunlukleri.com/" local="132285954502093284" remote="132241446000000000" Dst="0" />
<file name="meetup.svg" server="ftp.tulpartech.com/kahvegunlukleri.com/" local="132285954502343206" remote="132241446000000000" Dst="0" />
<file name="medium-m.svg" server="ftp.tulpartech.com/kahvegunlukleri.com/" local="132285954504042644" remote="132241446000000000" Dst="0" />
<file name="mendeley.svg" server="ftp.tulpartech.com/kahvegunlukleri.com/" local="132285954505462187" remote="132241446000000000" Dst="0" />
<file name="mix.svg" server="ftp.tulpartech.com/kahvegunlukleri.com/" local="132285954509600836" remote="132241446000000000" Dst="0" />
<file name="mixcloud.svg" server="ftp.tulpartech.com/kahvegunlukleri.com/" local="132285954509640829" remote="132241446000000000" Dst="0" />
<file name="microsoft.svg" server="ftp.tulpartech.com/kahvegunlukleri.com/" local="132285954509720807" remote="132241446000000000" Dst="0" />
<file name="mizuni.svg" server="ftp.tulpartech.com/kahvegunlukleri.com/" local="132285954510130674" remote="132241446000000000" Dst="0" />
<file name="modx.svg" server="ftp.tulpartech.com/kahvegunlukleri.com/" local="132285954510180669" remote="132241446000000000" Dst="0" />
<file name="neos.svg" server="ftp.tulpartech.com/kahvegunlukleri.com/" local="132285954511120343" remote="132241446000000000" Dst="0" />
<file name="nimblr.svg" server="ftp.tulpartech.com/kahvegunlukleri.com/" local="132285954512612558" remote="132241446000000000" Dst="0" />
<file name="napster.svg" server="ftp.tulpartech.com/kahvegunlukleri.com/" local="132285954512882509" remote="132241446000000000" Dst="0" />
<file name="monero.svg" server="ftp.tulpartech.com/kahvegunlukleri.com/" local="132285954512732568" remote="132241446000000000" Dst="0" />
<file name="nintendo-switch.svg" server="ftp.tulpartech.com/kahvegunlukleri.com/" local="132285954513202491" remote="132241446000000000" Dst="0" />
<file name="node-js.svg" server="ftp.tulpartech.com/kahvegunlukleri.com/" local="132285954513336076" remote="132241446000000000" Dst="0" />
<file name="npm.svg" server="ftp.tulpartech.com/kahvegunlukleri.com/" local="132285954515958914" remote="132241446000000000" Dst="0" />
<file name="ns8.svg" server="ftp.tulpartech.com/kahvegunlukleri.com/" local="132285954516428838" remote="132241446000000000" Dst="0" />
<file name="nutritionix.svg" server="ftp.tulpartech.com/kahvegunlukleri.com/" local="132285954516868663" remote="132241446000000000" Dst="0" />
<file name="odnoklassniki-square.svg" server="ftp.tulpartech.com/kahvegunlukleri.com/" local="132285954517078601" remote="132241446000000000" Dst="0" />
<file name="odnoklassniki.svg" server="ftp.tulpartech.com/kahvegunlukleri.com/" local="132285954517488458" remote="132241446000000000" Dst="0" />
<file name="opencart.svg" server="ftp.tulpartech.com/kahvegunlukleri.com/" local="132285954518038298" remote="132241446000000000" Dst="0" />
<file name="openid.svg" server="ftp.tulpartech.com/kahvegunlukleri.com/" local="132285954520277214" remote="132241446000000000" Dst="0" />
<file name="opera.svg" server="ftp.tulpartech.com/kahvegunlukleri.com/" local="132285954521287069" remote="132241446000000000" Dst="0" />
<file name="node.svg" server="ftp.tulpartech.com/kahvegunlukleri.com/" local="132285954522107450" remote="132241446000000000" Dst="0" />
<file name="osi.svg" server="ftp.tulpartech.com/kahvegunlukleri.com/" local="132285954524150875" remote="132241446000000000" Dst="0" />
<file name="optin-monster.svg" server="ftp.tulpartech.com/kahvegunlukleri.com/" local="132285954524310816" remote="132241446000000000" Dst="0" />
<file name="pagelines.svg" server="ftp.tulpartech.com/kahvegunlukleri.com/" local="132285954524900610" remote="132241446000000000" Dst="0" />
<file name="old-republic.svg" server="ftp.tulpartech.com/kahvegunlukleri.com/" local="132285954525605377" remote="132241446000000000" Dst="0" />
<file name="palfed.svg" server="ftp.tulpartech.com/kahvegunlukleri.com/" local="132285954526215272" remote="132241446000000000" Dst="0" />
<file name="patreon.svg" server="ftp.tulpartech.com/kahvegunlukleri.com/" local="132285954528878720" remote="132241446000000000" Dst="0" />
<file name="page4.svg" server="ftp.tulpartech.com/kahvegunlukleri.com/" local="132285954529378762" remote="132241446000000000" Dst="0" />
<file name="paypal.svg" server="ftp.tulpartech.com/kahvegunlukleri.com/" local="132285954529448746" remote="132241446000000000" Dst="0" />
<file name="penny-arcade.svg" server="ftp.tulpartech.com/kahvegunlukleri.com/" local="132285954529645458" remote="132241446000000000" Dst="0" />
<file name="periscope.svg" server="ftp.tulpartech.com/kahvegunlukleri.com/" local="132285954529935580" remote="132241446000000000" Dst="0" />
<file name="phabricator.svg" server="ftp.tulpartech.com/kahvegunlukleri.com/" local="132285954529985757" remote="132241446000000000" Dst="0" />
<file name="phoenix-framework.svg" server="ftp.tulpartech.com/kahvegunlukleri.com/" local="132285954530185502" remote="132241446000000000" Dst="0" />
<file name="pied-piper-alt.svg" server="ftp.tulpartech.com/kahvegunlukleri.com/" local="132285954530966012" remote="132241446000000000" Dst="0" />
<file name="pied-piper-hat.svg" server="ftp.tulpartech.com/kahvegunlukleri.com/" local="132285954532571790" remote="132241446000000000" Dst="0" />
<file name="php.svg" server="ftp.tulpartech.com/kahvegunlukleri.com/" local="132285954532781804" remote="132241446000000000" Dst="0" />
<file name="pied-piper.svg" server="ftp.tulpartech.com/kahvegunlukleri.com/" local="132285954533411564" remote="132241446000000000" Dst="0" />
<file name="phoenix-squadron.svg" server="ftp.tulpartech.com/kahvegunlukleri.com/" local="132285954533561514" remote="132241446000000000" Dst="0" />
<file name="pied-piper-pp.svg" server="ftp.tulpartech.com/kahvegunlukleri.com/" local="132285954535503810" remote="132241446000000000" Dst="0" />
<file name="pinterest-p.svg" server="ftp.tulpartech.com/kahvegunlukleri.com/" local="132285954538261545" remote="132241446000000000" Dst="0" />
<file name="pinterest-square.svg" server="ftp.tulpartech.com/kahvegunlukleri.com/" local="132285954539783263" remote="132241446000000000" Dst="0" />
<file name="playstation.svg" server="ftp.tulpartech.com/kahvegunlukleri.com/" local="132285954539963207" remote="132241446000000000" Dst="0" />
<file name="pinterest.svg" server="ftp.tulpartech.com/kahvegunlukleri.com/" local="132285954540552979" remote="132241446000000000" Dst="0" />
<file name="pushed.svg" server="ftp.tulpartech.com/kahvegunlukleri.com/" local="132285954540602958" remote="132241446000000000" Dst="0" />
<file name="product-hunt.svg" server="ftp.tulpartech.com/kahvegunlukleri.com/" local="132285954542855528" remote="132241446000000000" Dst="0" />
<file name="python.svg" server="ftp.tulpartech.com/kahvegunlukleri.com/" local="132285954543185397" remote="132241446000000000" Dst="0" />
<file name="qq.svg" server="ftp.tulpartech.com/kahvegunlukleri.com/" local="132285954543255511" remote="132241446000000000" Dst="0" />
<file name="quinscape.svg" server="ftp.tulpartech.com/kahvegunlukleri.com/" local="132285954543345341" remote="132241446000000000" Dst="0" />
<file name="quora.svg" server="ftp.tulpartech.com/kahvegunlukleri.com/" local="132285954543665232" remote="132241446000000000" Dst="0" />
<file name="r-project.svg" server="ftp.tulpartech.com/kahvegunlukleri.com/" local="132285954543745211" remote="132241446000000000" Dst="0" />
<file name="ravelry.svg" server="ftp.tulpartech.com/kahvegunlukleri.com/" local="132285954546374007" remote="132241446000000000" Dst="0" />
<file name="react.svg" server="ftp.tulpartech.com/kahvegunlukleri.com/" local="132285954548106088" remote="132241446000000000" Dst="0" />
<file name="reacteurope.svg" server="ftp.tulpartech.com/kahvegunlukleri.com/" local="132285954550032506" remote="132241446000000000" Dst="0" />
<file name="raspberry-pi.svg" server="ftp.tulpartech.com/kahvegunlukleri.com/" local="132285954551102572" remote="132241446000000000" Dst="0" />
<file name="red-river.svg" server="ftp.tulpartech.com/kahvegunlukleri.com/" local="132285954553201317" remote="132241446000000000" Dst="0" />
<file name="rebel.svg" server="ftp.tulpartech.com/kahvegunlukleri.com/" local="132285954553611187" remote="132241446000000000" Dst="0" />
<file name="reddit-alien.svg" server="ftp.tulpartech.com/kahvegunlukleri.com/" local="132285954554071013" remote="132241446000000000" Dst="0" />
<file name="readme.svg" server="ftp.tulpartech.com/kahvegunlukleri.com/" local="132285954555521134" remote="132241446000000000" Dst="0" />
<file name="reddit.svg" server="ftp.tulpartech.com/kahvegunlukleri.com/" local="132285954556140061" remote="132241446000000000" Dst="0" />
<file name="redhat.svg" server="ftp.tulpartech.com/kahvegunlukleri.com/" local="132285954558583202" remote="132241446000000000" Dst="0" />
<file name="reddit-square.svg" server="ftp.tulpartech.com/kahvegunlukleri.com/" local="132285954558733160" remote="132241446000000000" Dst="0" />
<file name="researchgate.svg" server="ftp.tulpartech.com/kahvegunlukleri.com/" local="132285954560330239" remote="132241446000000000" Dst="0" />
<file name="replyd.svg" server="ftp.tulpartech.com/kahvegunlukleri.com/" local="132285954561321629" remote="132241446000000000" Dst="0" />
<file name="rev.svg" server="ftp.tulpartech.com/kahvegunlukleri.com/" local="132285954563504737" remote="132241446000000000" Dst="0" />
<file name="resolving.svg" server="ftp.tulpartech.com/kahvegunlukleri.com/" local="132285954563694559" remote="132241446000000000" Dst="0" />
<file name="rocketchat.svg" server="ftp.tulpartech.com/kahvegunlukleri.com/" local="132285954564264483" remote="132241446000000000" Dst="0" />
<file name="rockrms.svg" server="ftp.tulpartech.com/kahvegunlukleri.com/" local="132285954566545176" remote="132241446000000000" Dst="0" />
<file name="safari.svg" server="ftp.tulpartech.com/kahvegunlukleri.com/" local="132285954566725104" remote="132241446000000000" Dst="0" />
<file name="renren.svg" server="ftp.tulpartech.com/kahvegunlukleri.com/" local="132285954567044971" remote="132241446000000000" Dst="0" />
<file name="salesforce.svg" server="ftp.tulpartech.com/kahvegunlukleri.com/" local="132285954567264895" remote="132241446000000000" Dst="0" />
<file name="sass.svg" server="ftp.tulpartech.com/kahvegunlukleri.com/" local="132285954567354866" remote="132241446000000000" Dst="0" />
<file name="schlix.svg" server="ftp.tulpartech.com/kahvegunlukleri.com/" local="132285954567544804" remote="132241446000000000" Dst="0" />
<file name="scribd.svg" server="ftp.tulpartech.com/kahvegunlukleri.com/" local="132285954567784726" remote="132241446000000000" Dst="0" />
<file name="searchengin.svg" server="ftp.tulpartech.com/kahvegunlukleri.com/" local="132285954567844710" remote="132241446000000000" Dst="0" />
<file name="sellsy.svg" server="ftp.tulpartech.com/kahvegunlukleri.com/" local="132285954568364574" remote="132241446000000000" Dst="0" />
<file name="servicestack.svg" server="ftp.tulpartech.com/kahvegunlukleri.com/" local="132285954568744427" remote="132241446000000000" Dst="0" />
<file name="shopware.svg" server="ftp.tulpartech.com/kahvegunlukleri.com/" local="132285954569575011" remote="132241446000000000" Dst="0" />
<file name="simplybuilt.svg" server="ftp.tulpartech.com/kahvegunlukleri.com/" local="132285954570184957" remote="132241446000000000" Dst="0" />
<file name="sellcast.svg" server="ftp.tulpartech.com/kahvegunlukleri.com/" local="132285954570574826" remote="132241446000000000" Dst="0" />
<file name="shirtsinbulk.svg" server="ftp.tulpartech.com/kahvegunlukleri.com/" local="132285954571735186" remote="132241446000000000" Dst="0" />
<file name="sketch.svg" server="ftp.tulpartech.com/kahvegunlukleri.com/" local="132285954573397711" remote="132241446000000000" Dst="0" />
<file name="sith.svg" server="ftp.tulpartech.com/kahvegunlukleri.com/" local="132285954573527362" remote="132241446000000000" Dst="0" />
<file name="skyatlas.svg" server="ftp.tulpartech.com/kahvegunlukleri.com/" local="132285954573997198" remote="132241446000000000" Dst="0" />
<file name="sistrix.svg" server="ftp.tulpartech.com/kahvegunlukleri.com/" local="132285954575417859" remote="132241446000000000" Dst="0" />
<file name="slack-hash.svg" server="ftp.tulpartech.com/kahvegunlukleri.com/" local="132285954575617786" remote="132241446000000000" Dst="0" />
<file name="skype.svg" server="ftp.tulpartech.com/kahvegunlukleri.com/" local="132285954578910755" remote="132241446000000000" Dst="0" />
<file name="slack.svg" server="ftp.tulpartech.com/kahvegunlukleri.com/" local="132285954579080538" remote="132241446000000000" Dst="0" />
<file name="slideshare.svg" server="ftp.tulpartech.com/kahvegunlukleri.com/" local="132285954579250474" remote="132241446000000000" Dst="0" />
<file name="snapchat-square.svg" server="ftp.tulpartech.com/kahvegunlukleri.com/" local="132285954579850272" remote="132241446000000000" Dst="0" />
<file name="snapchat-ghost.svg" server="ftp.tulpartech.com/kahvegunlukleri.com/" local="132285954581887606" remote="132241446000000000" Dst="0" />
<file name="snapchat.svg" server="ftp.tulpartech.com/kahvegunlukleri.com/" local="132285954582377560" remote="132241446000000000" Dst="0" />
<file name="sourcetree.svg" server="ftp.tulpartech.com/kahvegunlukleri.com/" local="132285954582807335" remote="132241446000000000" Dst="0" />
<file name="speakap.svg" server="ftp.tulpartech.com/kahvegunlukleri.com/" local="132285954582897315" remote="132241446000000000" Dst="0" />
<file name="speaker-deck.svg" server="ftp.tulpartech.com/kahvegunlukleri.com/" local="132285954583337855" remote="132241446000000000" Dst="0" />
<file name="spotify.svg" server="ftp.tulpartech.com/kahvegunlukleri.com/" local="132285954583427438" remote="132241446000000000" Dst="0" />
<file name="soundcloud.svg" server="ftp.tulpartech.com/kahvegunlukleri.com/" local="132285954584611445" remote="132241446000000000" Dst="0" />
<file name="stack-overflow.svg" server="ftp.tulpartech.com/kahvegunlukleri.com/" local="132285954585961639" remote="132241446000000000" Dst="0" />
<file name="squarespace.svg" server="ftp.tulpartech.com/kahvegunlukleri.com/" local="132285954586171544" remote="132241446000000000" Dst="0" />
<file name="stackpath.svg" server="ftp.tulpartech.com/kahvegunlukleri.com/" local="132285954586691361" remote="132241446000000000" Dst="0" />
<file name="staylinked.svg" server="ftp.tulpartech.com/kahvegunlukleri.com/" local="132285954586771342" remote="132241446000000000" Dst="0" />
<file name="stack-exchange.svg" server="ftp.tulpartech.com/kahvegunlukleri.com/" local="132285954588431799" remote="132241446000000000" Dst="0" />
<file name="steam.svg" server="ftp.tulpartech.com/kahvegunlukleri.com/" local="132285954594209269" remote="132241446000000000" Dst="0" />
<file name="steam-square.svg" server="ftp.tulpartech.com/kahvegunlukleri.com/" local="132285954594388920" remote="132241446000000000" Dst="0" />
<file name="steam-symbol.svg" server="ftp.tulpartech.com/kahvegunlukleri.com/" local="132285954594558850" remote="132241446000000000" Dst="0" />
<file name="sticker-mule.svg" server="ftp.tulpartech.com/kahvegunlukleri.com/" local="132285954599174759" remote="132241446000000000" Dst="0" />
<file name="stripe-s.svg" server="ftp.tulpartech.com/kahvegunlukleri.com/" local="132285954599484372" remote="132241446000000000" Dst="0" />
<file name="strava.svg" server="ftp.tulpartech.com/kahvegunlukleri.com/" local="132285954599644294" remote="132241446000000000" Dst="0" />
<file name="stripe.svg" server="ftp.tulpartech.com/kahvegunlukleri.com/" local="132285954600034158" remote="132241446000000000" Dst="0" />
<file name="studiovinari.svg" server="ftp.tulpartech.com/kahvegunlukleri.com/" local="132285954600084142" remote="132241446000000000" Dst="0" />
<file name="stumbleupon-circle.svg" server="ftp.tulpartech.com/kahvegunlukleri.com/" local="132285954600214099" remote="132241446000000000" Dst="0" />
<file name="stumbleupon.svg" server="ftp.tulpartech.com/kahvegunlukleri.com/" local="132285954600603968" remote="132241446000000000" Dst="0" />
<file name="superpowers.svg" server="ftp.tulpartech.com/kahvegunlukleri.com/" local="132285954600683953" remote="132241446000000000" Dst="0" />
<file name="supple.svg" server="ftp.tulpartech.com/kahvegunlukleri.com/" local="132285954600773916" remote="132241446000000000" Dst="0" />
<file name="symfony.svg" server="ftp.tulpartech.com/kahvegunlukleri.com/" local="132285954601143800" remote="132241446000000000" Dst="0" />
<file name="suse.svg" server="ftp.tulpartech.com/kahvegunlukleri.com/" local="132285954601213907" remote="132241446000000000" Dst="0" />
<file name="teamspeak.svg" server="ftp.tulpartech.com/kahvegunlukleri.com/" local="132285954601523675" remote="132241446000000000" Dst="0" />
<file name="telegram-plane.svg" server="ftp.tulpartech.com/kahvegunlukleri.com/" local="132285954601623644" remote="132241446000000000" Dst="0" />
<file name="telegram.svg" server="ftp.tulpartech.com/kahvegunlukleri.com/" local="132285954601713659" remote="132241446000000000" Dst="0" />
<file name="tencent-weibo.svg" server="ftp.tulpartech.com/kahvegunlukleri.com/" local="132285954602003519" remote="132241446000000000" Dst="0" />
<file name="themeisle.svg" server="ftp.tulpartech.com/kahvegunlukleri.com/" local="132285954602593326" remote="132241446000000000" Dst="0" />
<file name="themeco.svg" server="ftp.tulpartech.com/kahvegunlukleri.com/" local="132285954613592760" remote="132241446000000000" Dst="0" />
<file name="think-peaks.svg" server="ftp.tulpartech.com/kahvegunlukleri.com/" local="132285954613782704" remote="132241446000000000" Dst="0" />
<file name="the-red-yeti.svg" server="ftp.tulpartech.com/kahvegunlukleri.com/" local="132285954613972632" remote="132241446000000000" Dst="0" />
<file name="trello.svg" server="ftp.tulpartech.com/kahvegunlukleri.com/" local="132285954614693366" remote="132241446000000000" Dst="0" />
<file name="tumblr-square.svg" server="ftp.tulpartech.com/kahvegunlukleri.com/" local="132285954616382002" remote="132241446000000000" Dst="0" />
<file name="trade-federation.svg" server="ftp.tulpartech.com/kahvegunlukleri.com/" local="132285954616791866" remote="132241446000000000" Dst="0" />
<file name="tripadvisor.svg" server="ftp.tulpartech.com/kahvegunlukleri.com/" local="132285954616871824" remote="132241446000000000" Dst="0" />
<file name="tumblr.svg" server="ftp.tulpartech.com/kahvegunlukleri.com/" local="132285954619262466" remote="132241446000000000" Dst="0" />
<file name="twitch.svg" server="ftp.tulpartech.com/kahvegunlukleri.com/" local="132285954619472392" remote="132241446000000000" Dst="0" />
<file name="twitter-square.svg" server="ftp.tulpartech.com/kahvegunlukleri.com/" local="132285954619692307" remote="132241446000000000" Dst="0" />
<file name="twitter.svg" server="ftp.tulpartech.com/kahvegunlukleri.com/" local="132285954619802282" remote="132241446000000000" Dst="0" />
<file name="uber.svg" server="ftp.tulpartech.com/kahvegunlukleri.com/" local="132285954620342127" remote="132241446000000000" Dst="0" />
<file name="typo3.svg" server="ftp.tulpartech.com/kahvegunlukleri.com/" local="132285954622221596" remote="132241446000000000" Dst="0" />
<file name="ubuntu.svg" server="ftp.tulpartech.com/kahvegunlukleri.com/" local="132285954622411538" remote="132241446000000000" Dst="0" />
<file name="uikit.svg" server="ftp.tulpartech.com/kahvegunlukleri.com/" local="132285954624159092" remote="132241446000000000" Dst="0" />
<file name="uniregistry.svg" server="ftp.tulpartech.com/kahvegunlukleri.com/" local="132285954624859869" remote="132241446000000000" Dst="0" />
<file name="ups.svg" server="ftp.tulpartech.com/kahvegunlukleri.com/" local="132285954627056462" remote="132241446000000000" Dst="0" />
<file name="untappd.svg" server="ftp.tulpartech.com/kahvegunlukleri.com/" local="132285954627616275" remote="132241446000000000" Dst="0" />
<file name="usps.svg" server="ftp.tulpartech.com/kahvegunlukleri.com/" local="132285954627816198" remote="132241446000000000" Dst="0" />
<file name="ussunnah.svg" server="ftp.tulpartech.com/kahvegunlukleri.com/" local="132285954628116099" remote="132241446000000000" Dst="0" />
<file name="viacoin.svg" server="ftp.tulpartech.com/kahvegunlukleri.com/" local="132285954628575963" remote="132241446000000000" Dst="0" />
<file name="usb.svg" server="ftp.tulpartech.com/kahvegunlukleri.com/" local="132285954629196447" remote="132241446000000000" Dst="0" />
<file name="viadeo-square.svg" server="ftp.tulpartech.com/kahvegunlukleri.com/" local="132285954629476368" remote="132241446000000000" Dst="0" />
<file name="vaadin.svg" server="ftp.tulpartech.com/kahvegunlukleri.com/" local="132285954631017215" remote="132241446000000000" Dst="0" />
<file name="viber.svg" server="ftp.tulpartech.com/kahvegunlukleri.com/" local="132285954632621501" remote="132241446000000000" Dst="0" />
<file name="vimeo-v.svg" server="ftp.tulpartech.com/kahvegunlukleri.com/" local="132285954634130050" remote="132241446000000000" Dst="0" />
<file name="viadeo.svg" server="ftp.tulpartech.com/kahvegunlukleri.com/" local="132285954634379910" remote="132241446000000000" Dst="0" />
<file name="vimeo.svg" server="ftp.tulpartech.com/kahvegunlukleri.com/" local="132285954637477624" remote="132241446000000000" Dst="0" />
<file name="vk.svg" server="ftp.tulpartech.com/kahvegunlukleri.com/" local="132285954640894750" remote="132241446000000000" Dst="0" />
<file name="vnv.svg" server="ftp.tulpartech.com/kahvegunlukleri.com/" local="132285954655731752" remote="132241446000000000" Dst="0" />
<file name="vimeo-square.svg" server="ftp.tulpartech.com/kahvegunlukleri.com/" local="132285954655911559" remote="132241446000000000" Dst="0" />
<file name="vuejs.svg" server="ftp.tulpartech.com/kahvegunlukleri.com/" local="132285954656581584" remote="132241446000000000" Dst="0" />
<file name="waze.svg" server="ftp.tulpartech.com/kahvegunlukleri.com/" local="132285954656681578" remote="132241446000000000" Dst="0" />
<file name="weebly.svg" server="ftp.tulpartech.com/kahvegunlukleri.com/" local="132285954657041507" remote="132241446000000000" Dst="0" />
<file name="weibo.svg" server="ftp.tulpartech.com/kahvegunlukleri.com/" local="132285954657131485" remote="132241446000000000" Dst="0" />
<file name="weixin.svg" server="ftp.tulpartech.com/kahvegunlukleri.com/" local="132285954657561336" remote="132241446000000000" Dst="0" />
<file name="whatsapp-square.svg" server="ftp.tulpartech.com/kahvegunlukleri.com/" local="132285954657641310" remote="132241446000000000" Dst="0" />
<file name="whmcs.svg" server="ftp.tulpartech.com/kahvegunlukleri.com/" local="132285954658406748" remote="132241446000000000" Dst="0" />
<file name="whatsapp.svg" server="ftp.tulpartech.com/kahvegunlukleri.com/" local="132285954658556557" remote="132241446000000000" Dst="0" />
<file name="wikipedia-w.svg" server="ftp.tulpartech.com/kahvegunlukleri.com/" local="132285954659046384" remote="132241446000000000" Dst="0" />
<file name="vine.svg" server="ftp.tulpartech.com/kahvegunlukleri.com/" local="132285954673934070" remote="132241446000000000" Dst="0" />
<file name="wix.svg" server="ftp.tulpartech.com/kahvegunlukleri.com/" local="132285954674223992" remote="132241446000000000" Dst="0" />
<file name="wolf-pack-battalion.svg" server="ftp.tulpartech.com/kahvegunlukleri.com/" local="132285954674793763" remote="132241446000000000" Dst="0" />
<file name="windows.svg" server="ftp.tulpartech.com/kahvegunlukleri.com/" local="132285954676396633" remote="132241446000000000" Dst="0" />
<file name="wordpress-simple.svg" server="ftp.tulpartech.com/kahvegunlukleri.com/" local="132285954676486597" remote="132241446000000000" Dst="0" />
<file name="wizards-of-the-coast.svg" server="ftp.tulpartech.com/kahvegunlukleri.com/" local="132285954677977208" remote="132241446000000000" Dst="0" />
<file name="wordpress.svg" server="ftp.tulpartech.com/kahvegunlukleri.com/" local="132285954679499984" remote="132241446000000000" Dst="0" />
<file name="wpbeginner.svg" server="ftp.tulpartech.com/kahvegunlukleri.com/" local="132285954681341768" remote="132241446000000000" Dst="0" />
<file name="wpressr.svg" server="ftp.tulpartech.com/kahvegunlukleri.com/" local="132285954683260124" remote="132241446000000000" Dst="0" />
<file name="wpforms.svg" server="ftp.tulpartech.com/kahvegunlukleri.com/" local="132285954686243540" remote="132241446000000000" Dst="0" />
<file name="wpexplorer.svg" server="ftp.tulpartech.com/kahvegunlukleri.com/" local="132285954686423493" remote="132241446000000000" Dst="0" />
<file name="xing-square.svg" server="ftp.tulpartech.com/kahvegunlukleri.com/" local="132285954686943313" remote="132241446000000000" Dst="0" />
<file name="xbox.svg" server="ftp.tulpartech.com/kahvegunlukleri.com/" local="132285954689152553" remote="132241446000000000" Dst="0" />
<file name="xing.svg" server="ftp.tulpartech.com/kahvegunlukleri.com/" local="132285954691823999" remote="132241446000000000" Dst="0" />
<file name="y-combinator.svg" server="ftp.tulpartech.com/kahvegunlukleri.com/" local="132285954692003803" remote="132241446000000000" Dst="0" />
<file name="yahoo.svg" server="ftp.tulpartech.com/kahvegunlukleri.com/" local="132285954692383657" remote="132241446000000000" Dst="0" />
<file name="yammer.svg" server="ftp.tulpartech.com/kahvegunlukleri.com/" local="132285954692673554" remote="132241446000000000" Dst="0" />
<file name="yandex-international.svg" server="ftp.tulpartech.com/kahvegunlukleri.com/" local="132285954692723539" remote="132241446000000000" Dst="0" />
<file name="yandex.svg" server="ftp.tulpartech.com/kahvegunlukleri.com/" local="132285954692933472" remote="132241446000000000" Dst="0" />
<file name="yelp.svg" server="ftp.tulpartech.com/kahvegunlukleri.com/" local="132285954693253367" remote="132241446000000000" Dst="0" />
<file name="yoast.svg" server="ftp.tulpartech.com/kahvegunlukleri.com/" local="132285954693453663" remote="132241446000000000" Dst="0" />
<file name="youtube-square.svg" server="ftp.tulpartech.com/kahvegunlukleri.com/" local="132285954693733450" remote="132241446000000000" Dst="0" />
<file name="zhihu.svg" server="ftp.tulpartech.com/kahvegunlukleri.com/" local="132285954695273189" remote="132241446000000000" Dst="0" />
<file name="yarn.svg" server="ftp.tulpartech.com/kahvegunlukleri.com/" local="132285954695473104" remote="132241446000000000" Dst="0" />
<file name="youtube.svg" server="ftp.tulpartech.com/kahvegunlukleri.com/" local="132285954701218095" remote="132241446000000000" Dst="0" />
</dwsync>